speccaf/__init__.py
speccaf/solver.py
speccaf/spherical.py
speccaf/data/MatricesL12.npz
speccaf/data/MatricesL20.npz
speccaf/data/MatricesL4.npz
speccaf/data/MatricesL6.npz
speccaf/data/MatricesL8.npz
speccaf-1.4.4.dist-info/LICENSE
speccaf-1.4.4.dist-info/METADATA
speccaf-1.4.4.dist-info/WHEEL
speccaf-1.4.4.dist-info/top_level.txt
speccaf-1.4.4.dist-info/RECORD
