Metadata-Version: 2.1
Name: speccaf
Version: 1.4.4
Summary: Python implementation of a Spectral Continuum Anisotropic Fabric evolution model
Home-page: https://github.com/danrichards678/SpecCAF
Author: Daniel Richards
Author-email: danrichards678@gmail.com
License: MIT
Classifier: Intended Audience :: Science/Research
Classifier: License :: OSI Approved :: MIT License
Classifier: Operating System :: OS Independent
Classifier: Programming Language :: Python :: 3
License-File: LICENSE
Requires-Dist: numpy
Requires-Dist: scipy
